LICENSE
MANIFEST.in
README.markdown
flask_login.py
setup.py
quokka_flask_login.egg-info/PKG-INFO
quokka_flask_login.egg-info/SOURCES.txt
quokka_flask_login.egg-info/dependency_links.txt
quokka_flask_login.egg-info/not-zip-safe
quokka_flask_login.egg-info/requires.txt
quokka_flask_login.egg-info/top_level.txt